prometheus/__init__.py
prometheus/allfit.py
prometheus/aperture.py
prometheus/ccddata.py
prometheus/ckdtree.py
prometheus/completeness.py
prometheus/detection.py
prometheus/fast.py
prometheus/forced.py
prometheus/galfit.py
prometheus/getpsf.py
prometheus/groupfit.py
prometheus/groupstars.py
prometheus/kd_tree.py
prometheus/ladfit.py
prometheus/leastsquares.py
prometheus/models.py
prometheus/multifit.py
prometheus/prometheus.py
prometheus/sdss_deblender.py
prometheus/sky.py
prometheus/synth.py
prometheus/utils.py
prometheus/cython/fastarray.pxd
prometheus/cython/fastarray.pyx
prometheus/cython/gaussian.pyx
prometheus/cython/getpsf.pyx
prometheus/cython/models.pyx
prometheus/cython/tests_cython.py
prometheus/cython/utils.pxd
prometheus/cython/utils.pyx
prometheus/numba/allfit_jitclass_numba.py
prometheus/numba/allfit_numba.py
prometheus/numba/allfit_numba_static.py
prometheus/numba/clock_numba.py
prometheus/numba/coords_numba_static.py
prometheus/numba/getpsf_numba.py
prometheus/numba/getpsf_numba_static.py
prometheus/numba/groupfit_jitclass_numba.py
prometheus/numba/groupfit_numba.py
prometheus/numba/groupfit_numba_static.py
prometheus/numba/ladfit_numba_static.py
prometheus/numba/models_numba.py
prometheus/numba/models_numba_static.py
prometheus/numba/tests_numba.py
prometheus/numba/tests_numba_static.py
prometheus/numba/utils_numba.py
prometheus/numba/utils_numba_static.py
theprometheus-1.0.27.data/scripts/prometheus
theprometheus-1.0.27.dist-info/licenses/LICENSE
theprometheus-1.0.27.dist-info/METADATA
theprometheus-1.0.27.dist-info/WHEEL
theprometheus-1.0.27.dist-info/top_level.txt
theprometheus-1.0.27.dist-info/RECORD
