Metadata-Version: 2.4
Name: theprometheus
Version: 1.0.27
Summary: PSF Photometry Software
Home-page: https://github.com/dnidever/prometheus
Author: David Nidever
Author-email: David Nidever <dnidever@montana.edu>
Maintainer-email: David Nidever <dnidever@montana.edu>
License: MIT License
Project-URL: Documentation, https://prometheus.readthedocs.org
Project-URL: Repository, https://github.com/dnidever/prometheus
Keywords: imaging,photometry,PSF
Classifier: Development Status :: 3 - Alpha
Classifier: License :: OSI Approved :: MIT License
Classifier: Programming Language :: Python
Requires: numpy
Requires: astropy(>=4.0)
Requires: scipy
Requires: dlnpyutils
Requires: sep
Requires: extension_helpers
Requires: photutils
Requires: skimage
Requires: dill
Requires-Python: >=3.9
License-File: LICENSE
Requires-Dist: numpy
Requires-Dist: scipy
Requires-Dist: dlnpyutils
Requires-Dist: sep
Requires-Dist: extension_helpers
Requires-Dist: photutils
Requires-Dist: skimage
Requires-Dist: dill
Provides-Extra: gui
Requires-Dist: PyQt5; extra == "gui"
Provides-Extra: cli
Requires-Dist: rich; extra == "cli"
Requires-Dist: click; extra == "cli"
Dynamic: author
Dynamic: home-page
Dynamic: license-file
Dynamic: requires
